waller/__init__.py
waller/__main__.py
waller/ldm_gtk.py
waller/waller.py
waller-0.3.6.dist-info/LICENSE
waller-0.3.6.dist-info/METADATA
waller-0.3.6.dist-info/WHEEL
waller-0.3.6.dist-info/entry_points.txt
waller-0.3.6.dist-info/top_level.txt
waller-0.3.6.dist-info/RECORD
