Metadata-Version: 2.1
Name: waller
Version: 0.3.6
Summary: Python curses utility to cycle between desktop wallpapers
Home-page: https://github.com/codeswhite/waller
Author: Max G
Author-email: max3227@gmail.com
License: UNKNOWN
Platform: UNKNOWN
Classifier: Programming Language :: Python :: 3
Classifier: License :: OSI Approved :: MIT License
Classifier: Operating System :: Unix
Requires-Python: >=3.6
